haruka_bot_red/__init__.py
haruka_bot_red/__main__.py
haruka_bot_red/cli/__init__.py
haruka_bot_red/cli/bot.py
haruka_bot_red/cli/utils.py
haruka_bot_red/config.py
haruka_bot_red/database/__init__.py
haruka_bot_red/database/db.py
haruka_bot_red/database/models.py
haruka_bot_red/libs/__init__.py
haruka_bot_red/libs/dynamic/__init__.py
haruka_bot_red/libs/dynamic/card.py
haruka_bot_red/libs/dynamic/desc.py
haruka_bot_red/libs/dynamic/display.py
haruka_bot_red/libs/dynamic/user_profile.py
haruka_bot_red/plugins/__init__.py
haruka_bot_red/plugins/at/__init__.py
haruka_bot_red/plugins/at/at_off.py
haruka_bot_red/plugins/at/at_on.py
haruka_bot_red/plugins/dynamic/__init__.py
haruka_bot_red/plugins/dynamic/dynamic_off.py
haruka_bot_red/plugins/dynamic/dynamic_on.py
haruka_bot_red/plugins/help.py
haruka_bot_red/plugins/live/__init__.py
haruka_bot_red/plugins/live/live_now.py
haruka_bot_red/plugins/live/live_off.py
haruka_bot_red/plugins/live/live_on.py
haruka_bot_red/plugins/permission/__init__.py
haruka_bot_red/plugins/permission/permission_off.py
haruka_bot_red/plugins/permission/permission_on.py
haruka_bot_red/plugins/pusher/__init__.py
haruka_bot_red/plugins/pusher/dynamic_pusher.py
haruka_bot_red/plugins/pusher/live_pusher.py
haruka_bot_red/plugins/sub/__init__.py
haruka_bot_red/plugins/sub/add_sub.py
haruka_bot_red/plugins/sub/delete_sub.py
haruka_bot_red/plugins/sub/sub_list.py
haruka_bot_red/utils/__init__.py
haruka_bot_red/utils/browser.py
haruka_bot_red/utils/fonts_provider.py
haruka_bot_red/utils/get_dynamic_list.py
haruka_bot_red/utils/mobile.js
haruka_bot_red/version.py
haruka_bot_red-0.1.7.dist-info/entry_points.txt
haruka_bot_red-0.1.7.dist-info/WHEEL
haruka_bot_red-0.1.7.dist-info/METADATA
haruka_bot_red-0.1.7.dist-info/licenses/LICENSE
haruka_bot_red-0.1.7.dist-info/RECORD
